{"NjsabPfc78QlibAjBBEmrQ==":"img_3682_polarr-1368x912.jpeg","3w6QqHFmM4D6qgJ11rTisg==":"img_3682_polarr-736x491.jpeg","OM6hTwqMAQpTVhLcPG86xg==":"background1.jpg","SuPdOhnQUYuMY3BQYOnUVg==":"img_3682_polarr-1162x775.jpeg","Zv/XnrYt8fWjB886fZIbkQ==":"img-9762-2000x1333.jpeg","hBoq9KJoFPkOpaGp4HUkVg==":"img_1917_polarr-1162x1743.jpeg","xYQzs8ewekXDfANkSYZ02A==":"img-5350-122x244.jpeg","3VknSYZbxg5WET8eOXoBIg==":"img-5350-192x385.jpeg","CBbSw9Us3zwlFwNl7E18Lg==":"%E5%8D%97%E4%BA%AC%E5%A4%A7%E5%AD%A6%E6%A0%A1%E5%BE%BD-266x324.jpeg","R0Pl13YQtswEjEjn9XGX0A==":"img-3923-696x1237.png","2d/R4xBIvCCfwWcfEB4fsQ==":"img-3924-696x1237.png","zhlcpC0DdyLD66mo1wPxag==":"img-3925-696x1237.png","K666FTw5ebkqmWAaDwS9iA==":"img-3926-696x1237.png","qtaIY6wdizpEiJr0r5iuig==":"img-3927-696x1237.png","O9e+8ryqtPq50TCXN0holA==":"img-3928-696x1237.png","WEZ1S+9GdVfumSuuw+MCIw==":"img-3919-696x683.jpg","dhtGC41gwzaVjahzfIR+WA==":"img-5345-696x752.jpeg","5sSWeHG4EOg6QqR4CuHqiQ==":"%E5%8D%97%E4%BA%AC%E5%A4%A7%E5%AD%A6%E6%A0%A1%E5%BE%BD-266x324.jpeg","hFKW5AeR07C0aJPwzR7plQ==":"%E5%90%B4%E8%8E%89logo-184x184.png"}